desksnake/__init__.py
desksnake/desksnake.py
desksnake-0.0.1.dist-info/LICENSE
desksnake-0.0.1.dist-info/METADATA
desksnake-0.0.1.dist-info/WHEEL
desksnake-0.0.1.dist-info/entry_points.txt
desksnake-0.0.1.dist-info/top_level.txt
desksnake-0.0.1.dist-info/RECORD
